odoo/addons/lead_2_opportunity_default_action/README.rst
odoo/addons/lead_2_opportunity_default_action/__init__.py
odoo/addons/lead_2_opportunity_default_action/__manifest__.py
odoo/addons/lead_2_opportunity_default_action/data/ir_config_parameter_data.xml
odoo/addons/lead_2_opportunity_default_action/readme/CONFIGURE.md
odoo/addons/lead_2_opportunity_default_action/readme/CONTRIBUTORS.md
odoo/addons/lead_2_opportunity_default_action/readme/DESCRIPTION.md
odoo/addons/lead_2_opportunity_default_action/static/description/icon.png
odoo/addons/lead_2_opportunity_default_action/static/description/index.html
odoo/addons/lead_2_opportunity_default_action/tests/__init__.py
odoo/addons/lead_2_opportunity_default_action/tests/test_lead_2_opportunity_default.py
odoo/addons/lead_2_opportunity_default_action/wizard/__init__.py
odoo/addons/lead_2_opportunity_default_action/wizard/crm_lead2opportunity_partner.py
odoo/addons/lead_2_opportunity_default_action/wizard/crm_lead2opportunity_partner_mass.py
odoo_addon_lead_2_opportunity_default_action-17.0.1.0.0.1.dist-info/METADATA
odoo_addon_lead_2_opportunity_default_action-17.0.1.0.0.1.dist-info/WHEEL
odoo_addon_lead_2_opportunity_default_action-17.0.1.0.0.1.dist-info/top_level.txt
odoo_addon_lead_2_opportunity_default_action-17.0.1.0.0.1.dist-info/RECORD
